odoo/addons/ssi_risk_analysis_reference_document/README.rst
odoo/addons/ssi_risk_analysis_reference_document/__init__.py
odoo/addons/ssi_risk_analysis_reference_document/__manifest__.py
odoo/addons/ssi_risk_analysis_reference_document/models/__init__.py
odoo/addons/ssi_risk_analysis_reference_document/models/risk_analysis.py
odoo/addons/ssi_risk_analysis_reference_document/models/risk_analysis_type.py
odoo/addons/ssi_risk_analysis_reference_document/static/description/icon.png
odoo/addons/ssi_risk_analysis_reference_document/views/risk_analysis_type_views.xml
odoo14_addon_ssi_risk_analysis_reference_document-14.0.1.0.0.dist-info/METADATA
odoo14_addon_ssi_risk_analysis_reference_document-14.0.1.0.0.dist-info/WHEEL
odoo14_addon_ssi_risk_analysis_reference_document-14.0.1.0.0.dist-info/top_level.txt
odoo14_addon_ssi_risk_analysis_reference_document-14.0.1.0.0.dist-info/RECORD
